pyHTTPServer/HTTPServer.py
pyHTTPServer/__init__.py
pyHTTPServer-0.1.6.dist-info/LICENSE.md
pyHTTPServer-0.1.6.dist-info/METADATA
pyHTTPServer-0.1.6.dist-info/WHEEL
pyHTTPServer-0.1.6.dist-info/top_level.txt
pyHTTPServer-0.1.6.dist-info/RECORD
