Metadata-Version: 2.1
Name: pyHTTPServer
Version: 0.1.6
Summary: An HTTP Server implementation offering a pyHTTPInterface.
Home-page: https://github.com/Paebbels/pyHTTPServer
Author: Patrick Lehmann
Author-email: Paebbels@gmail.com
License: UNKNOWN
Project-URL: Documentation, https://pyHTTPServer.readthedocs.io/en/latest/
Project-URL: Source Code, https://github.com/Paebbels/pyHTTPServer
Project-URL: Issue Tracker, https://github.com/Paebbels/pyHTTPServer/issues
Keywords: Python3 HTTP-Server
Platform: UNKNOWN
Classifier: License :: OSI Approved :: Apache Software License
Classifier: Operating System :: OS Independent
Classifier: Programming Language :: Python :: 3 :: Only
Classifier: Programming Language :: Python :: 3.5
Classifier: Programming Language :: Python :: 3.6
Classifier: Programming Language :: Python :: 3.7
Classifier: Programming Language :: Python :: 3.8
Classifier: Development Status :: 2 - Pre-Alpha
Classifier: Intended Audience :: Developers
Classifier: Topic :: Internet :: WWW/HTTP :: HTTP Servers
Classifier: Topic :: Utilities
Requires-Python: >=3.5
Requires-Dist: py-flags
Requires-Dist: pyExceptions
Requires-Dist: pyHTTPInterface
